saintcord/__init__.py
saintcord-2.0.1.dist-info/METADATA
saintcord-2.0.1.dist-info/WHEEL
saintcord-2.0.1.dist-info/top_level.txt
saintcord-2.0.1.dist-info/RECORD
